{
  "data": {
    "article": {},
    "attachments": {},
    "author_id": "1124790071314587648",
    "conversation_id": "2068037346243891417",
    "created_at": "2026-06-20T04:44:14.000Z",
    "edit_controls": {
      "editable_until": "2026-06-20T05:44:14.000Z",
      "edits_remaining": 5,
      "is_edit_eligible": false
    },
    "edit_history_tweet_ids": [
      "2068193183935394122"
    ],
    "entities": {
      "mentions": [
        {
          "end": 14,
          "id": "1445681460497694723",
          "start": 0,
          "username": "cryptochenrui"
        }
      ]
    },
    "geo": {},
    "id": "2068193183935394122",
    "in_reply_to_user_id": "1445681460497694723",
    "lang": "ja",
    "note_tweet": {
      "entities": {}
    },
    "possibly_sensitive": false,
    "public_metrics": {
      "bookmark_count": 0,
      "impression_count": 0,
      "like_count": 0,
      "quote_count": 0,
      "reply_count": 0,
      "retweet_count": 0
    },
    "referenced_tweets": [
      {
        "id": "2068175054794588355",
        "type": "replied_to"
      }
    ],
    "reply_settings": "everyone",
    "text": "@cryptochenrui 😭😭😭不敢了"
  },
  "includes": {
    "tweets": [
      {
        "article": {},
        "attachments": {},
        "author_id": "1124790071314587648",
        "conversation_id": "2068037346243891417",
        "created_at": "2026-06-20T04:44:14.000Z",
        "edit_controls": {
          "editable_until": "2026-06-20T05:44:14.000Z",
          "edits_remaining": 5,
          "is_edit_eligible": false
        },
        "edit_history_tweet_ids": [
          "2068193183935394122"
        ],
        "entities": {
          "mentions": [
            {
              "end": 14,
              "id": "1445681460497694723",
              "start": 0,
              "username": "cryptochenrui"
            }
          ]
        },
        "geo": {},
        "id": "2068193183935394122",
        "in_reply_to_user_id": "1445681460497694723",
        "lang": "ja",
        "note_tweet": {
          "entities": {}
        },
        "possibly_sensitive": false,
        "public_metrics": {
          "bookmark_count": 0,
          "impression_count": 0,
          "like_count": 0,
          "quote_count": 0,
          "reply_count": 0,
          "retweet_count": 0
        },
        "referenced_tweets": [
          {
            "id": "2068175054794588355",
            "type": "replied_to"
          }
        ],
        "reply_settings": "everyone",
        "text": "@cryptochenrui 😭😭😭不敢了"
      },
      {
        "article": {},
        "attachments": {},
        "author_id": "1445681460497694723",
        "conversation_id": "2068037346243891417",
        "created_at": "2026-06-20T03:32:12.000Z",
        "edit_controls": {
          "editable_until": "2026-06-20T04:32:12.000Z",
          "edits_remaining": 5,
          "is_edit_eligible": false
        },
        "edit_history_tweet_ids": [
          "2068175054794588355"
        ],
        "entities": {
          "mentions": [
            {
              "end": 13,
              "id": "1124790071314587648",
              "start": 0,
              "username": "LanwujiDrink"
            }
          ]
        },
        "geo": {},
        "id": "2068175054794588355",
        "in_reply_to_user_id": "1124790071314587648",
        "lang": "zh",
        "note_tweet": {
          "entities": {}
        },
        "possibly_sensitive": false,
        "public_metrics": {
          "bookmark_count": 0,
          "impression_count": 14,
          "like_count": 0,
          "quote_count": 0,
          "reply_count": 1,
          "retweet_count": 0
        },
        "referenced_tweets": [
          {
            "id": "2068037346243891417",
            "type": "replied_to"
          }
        ],
        "reply_settings": "everyone",
        "text": "@LanwujiDrink 像是会给你肚子上来两下"
      }
    ],
    "users": [
      {
        "created_at": "2019-05-04T21:37:05.000Z",
        "description": "打电竞刷题就喝無極電競能量",
        "id": "1124790071314587648",
        "location": "和田地区！",
        "name": "☯️🧬無極电竞能量",
        "profile_image_url": "https://pbs.twimg.com/profile_images/2066224286881427456/d1iNxUPE_normal.jpg",
        "protected": false,
        "public_metrics": {
          "followers_count": 247,
          "following_count": 121,
          "like_count": 2758,
          "listed_count": 0,
          "media_count": 10,
          "tweet_count": 736
        },
        "url": "",
        "username": "LanwujiDrink",
        "verified": true
      },
      {
        "created_at": "2021-10-06T09:25:19.000Z",
        "description": "这里是精神病和嗑药od频道.\n大学退学。intj。\n欢迎温良边缘人直fo。\n🈲过激健全基本盘男权女权。\n交易员频道是@chenrui2025",
        "entities": {
          "description": {
            "mentions": [
              {
                "end": 70,
                "start": 58,
                "username": "chenrui2025"
              }
            ]
          }
        },
        "id": "1445681460497694723",
        "location": "南昌",
        "name": "relife栗子",
        "profile_image_url": "https://pbs.twimg.com/profile_images/2034259613885796353/B-zmpLFS_normal.jpg",
        "protected": false,
        "public_metrics": {
          "followers_count": 214,
          "following_count": 256,
          "like_count": 9497,
          "listed_count": 5,
          "media_count": 130,
          "tweet_count": 2402
        },
        "url": "",
        "username": "cryptochenrui",
        "verified": false
      }
    ]
  }
}